kim_tools/__init__.py
kim_tools/kimunits.py
kim_tools/aflow_util/__init__.py
kim_tools/aflow_util/core.py
kim_tools/aflow_util/data/README_PROTO.TXT
kim_tools/ase/__init__.py
kim_tools/ase/core.py
kim_tools/symmetry_util/__init__.py
kim_tools/symmetry_util/core.py
kim_tools/symmetry_util/data/possible_primitive_shifts.json
kim_tools/symmetry_util/data/primitive_GENPOS_ops.json
kim_tools/symmetry_util/data/space_groups_for_each_bravais_lattice.json
kim_tools/symmetry_util/data/wyck_pos_xform_under_normalizer.json
kim_tools/symmetry_util/data/wyckoff_multiplicities.json
kim_tools/symmetry_util/data/wyckoff_sets.json
kim_tools/test_driver/__init__.py
kim_tools/test_driver/core.py
kim_tools/vc/__init__.py
kim_tools/vc/core.py
kim_tools-0.2.5.dist-info/licenses/LICENSE.CDDL
kim_tools-0.2.5.dist-info/METADATA
kim_tools-0.2.5.dist-info/WHEEL
kim_tools-0.2.5.dist-info/top_level.txt
kim_tools-0.2.5.dist-info/RECORD
